Workbook

Sheet Dashboard
A1: Personal Finance & Budgeting Model for College Students
A2: Excel portfolio project • Edit the blue input cells to personalize the model
A4: Monthly Income | C4: Monthly Expenses | E4: Monthly Savings | G4: Savings Rate
A5: ='Budget Planner'!B4 | C5: ='Budget Planner'!B16 | E5: ='Budget Planner'!B17 | G5: ='Budget Planner'!B18
A8: Spending Overview
A9: Category | B9: Monthly Budget | C9: Actual Expense
A10: Food | B10: ='Budget Planner'!B6 | C10: ='Budget Planner'!C6
A11: Transportation | B11: ='Budget Planner'!B7 | C11: ='Budget Planner'!C7
A12: Education | B12: ='Budget Planner'!B8 | C12: ='Budget Planner'!C8
A13: Mobile/Internet | B13: ='Budget Planner'!B9 | C13: ='Budget Planner'!C9
A14: Entertainment | B14: ='Budget Planner'!B10 | C14: ='Budget Planner'!C10
A15: Personal | B15: ='Budget Planner'!B11 | C15: ='Budget Planner'!C11
A16: Emergency Fund | B16: ='Budget Planner'!B12 | C16: ='Budget Planner'!C12

Sheet Budget Planner
A1: Monthly Budget Planner
A3: Input / Summary
A4: Monthly Income | B4: 15000
A5: Savings Goal | B5: 3000
A7: Category | B7: Budget | C7: Actual | D7: Variance
A8: Food | B8: 3000 | C8: 2800 | D8: =B8-C8
A9: Transportation | B9: 1500 | C9: 1200 | D9: =B9-C9
A10: Education | B10: 2000 | C10: 1800 | D10: =B10-C10
A11: Mobile/Internet | B11: 800 | C11: 700 | D11: =B11-C11
A12: Entertainment | B12: 1200 | C12: 1400 | D12: =B12-C12
A13: Personal | B13: 1000 | C13: 900 | D13: =B13-C13
A14: Emergency Fund | B14: 1500 | C14: 1500 | D14: =B14-C14
A16: Total Expenses | B16: =SUM(B8:B14) | C16: =SUM(C8:C14) | D16: =B16-C16
A17: Monthly Savings | B17: =B4-C16 | C17: =B4-C16
A18: Savings Rate | B18: =B17/B4 | C18: =B17/B4

Sheet Expense Tracker
A1: Expense Tracker
A3: Date | B3: Category | C3: Description | D3: Amount (₹) | E3: Payment Method | F3: Notes
A4: 2026-10-01 | B4: Food | C4: Lunch | D4: 180 | E4: UPI
A5: 2026-10-01 | B5: Transportation | C5: Bus | D5: 40 | E5: Cash
A6: 2026-10-02 | B6: Education | C6: Notebook | D6: 120 | E6: UPI
A7: 2026-10-03 | B7: Entertainment | C7: Movie | D7: 250 | E7: UPI
A8: 2026-10-04 | B8: Personal | C8: Stationery | D8: 90 | E8: Cash

Sheet Savings Goals
A1: Savings Goal Calculator
A3: Goal | B3: Target Amount (₹) | C3: Current Savings (₹) | D3: Monthly Contribution (₹) | E3: Remaining (₹) | F3: Months Needed
A4: Emergency Fund | B4: 30000 | C4: 5000 | D4: 2500 | E4: =MAX(0,B4-C4) | F4: =IF(D4>0,ROUNDUP(E4/D4,0),"—")
A5: Laptop | B5: 50000 | C5: 10000 | D5: 4000 | E5: =MAX(0,B5-C5) | F5: =IF(D5>0,ROUNDUP(E5/D5,0),"—")
A6: Japan Study Fund | B6: 100000 | C6: 15000 | D6: 5000 | E6: =MAX(0,B6-C6) | F6: =IF(D6>0,ROUNDUP(E6/D6,0),"—")
E7: =IF(B7="","",MAX(0,B7-C7)) | F7: =IF(OR(B7="",D7=""),"",ROUNDUP(E7/D7,0))
E8: =IF(B8="","",MAX(0,B8-C8)) | F8: =IF(OR(B8="",D8=""),"",ROUNDUP(E8/D8,0))
E9: =IF(B9="","",MAX(0,B9-C9)) | F9: =IF(OR(B9="",D9=""),"",ROUNDUP(E9/D9,0))
E10: =IF(B10="","",MAX(0,B10-C10)) | F10: =IF(OR(B10="",D10=""),"",ROUNDUP(E10/D10,0))
E11: =IF(B11="","",MAX(0,B11-C11)) | F11: =IF(OR(B11="",D11=""),"",ROUNDUP(E11/D11,0))

Sheet What-If Analysis
A1: What-If Savings Analysis
A3: Scenario | B3: Monthly Income | C3: Monthly Expenses | D3: Monthly Savings | E3: Savings Rate | F3: Annual Savings
A4: Current Budget | B4: 15000 | C4: 10300 | D4: =B4-C4 | E4: =D4/B4 | F4: =D4*12
A5: Reduce Entertainment by ₹500 | B5: 15000 | C5: 9800 | D5: =B5-C5 | E5: =D5/B5 | F5: =D5*12
A6: Reduce Food + Entertainment by ₹1,000 | B6: 15000 | C6: 9300 | D6: =B6-C6 | E6: =D6/B6 | F6: =D6*12
A9: How to use
A10: Edit the income and expense assumptions in rows 4–6 to test how spending changes affect monthly and annual savings. Keep assumptions realistic and document your reasoning in your project report.

Sheet Project Guide
A1: Project Guide & Resume Notes
A3: Project Title | B3: Personal Finance & Budgeting Model for College Students
A4: Objective | B4: Build a practical Excel model for tracking expenses, managing a monthly budget, setting savings goals and testing spending scenarios.
A5: Tools | B5: Microsoft Excel / Google Sheets
A6: Key Skills | B6: Excel formulas, budgeting, financial analysis, data organization, dashboard creation, what-if analysis
A7: Suggested Evidence | B7: Keep screenshots of the dashboard, budget planner, savings goals and what-if analysis for your portfolio.
A8: Interview Explanation | B8: Explain the assumptions, formulas, dashboard design and how changing expenses affects savings.
A9: Resume Tip | B9: List the project after completing and testing it. Mention only features you can confidently demonstrate.
